[
  {
    "id": 1,
    "bankId": "37e8acce-74db-11ef-9509-c7c02480418f",
    "cardNumber": "5342711066962018",
    "cvv": "023",
    "name": "Zeyad Tarek tolan",
    "expireDate": "09/30",
    "type": "mastercard",
    "userId": 4,
    "balance": 150,
    "status": "active",
    "createdAt": "2024-10-24T23:39:05.521",
    "updatedAt": "2024-10-24T23:39:05.521"
  },
  {
    "id": 2,
    "bankId": "cdbb21cc-6c58-11ef-adac-5731fd339c74",
    "cardNumber": "5342711087501589",
    "cvv": "525",
    "name": "Mohamed",
    "expireDate": "09/30",
    "type": "mastercard",
    "userId": 5,
    "balance": 1,
    "status": "active",
    "createdAt": "2024-10-25T00:08:16.818",
    "updatedAt": "2024-10-25T00:08:16.818"
  },
  {
    "id": 27,
    "bankId": "ec3a67c8-94b4-11ef-9b06-a78e92d18326",
    "cardNumber": "5342711027722535",
    "cvv": "295",
    "name": "Mustafa Saber",
    "expireDate": "10/25",
    "type": "mastercard",
    "userId": 13,
    "balance": 5,
    "status": "active",
    "createdAt": "2024-10-27T22:44:19.396",
    "updatedAt": "2024-10-27T22:44:19.396"
  },
  {
    "id": 4,
    "bankId": "9ea29e98-92cc-11ef-a125-9b70300f9526",
    "cardNumber": "5342711023849985",
    "cvv": "294",
    "name": "Rrr",
    "expireDate": "10/25",
    "type": "mastercard",
    "userId": 10,
    "balance": 205,
    "status": "active",
    "createdAt": "2024-10-25T12:28:50.882",
    "updatedAt": "2024-10-28T11:48:59.632"
  },
  {
    "id": 38,
    "bankId": "c9177012-aeb1-11ef-b17b-633b62c47966",
    "cardNumber": "5342711032541060",
    "cvv": "366",
    "name": "Sayed",
    "expireDate": "11/25",
    "type": "mastercard",
    "userId": 58,
    "balance": 5,
    "status": "active",
    "createdAt": "2024-11-30T00:27:26.305",
    "updatedAt": "2024-11-30T00:27:26.305"
  },
  {
    "id": 29,
    "bankId": "6671465a-8c00-11ef-87a6-bb0fa77d7cd6",
    "cardNumber": "5342711009122225",
    "cvv": "810",
    "name": "Mohamed Salah Mohamed",
    "expireDate": "10/25",
    "type": "mastercard",
    "userId": 20,
    "balance": 35,
    "status": "active",
    "createdAt": "2024-11-01T13:43:56.351",
    "updatedAt": "2024-11-01T13:43:56.351"
  },
  {
    "id": 65,
    "bankId": "4ba5e9ee-b53a-11ef-9575-7f68b0378423",
    "cardNumber": "5342711061382352",
    "cvv": "299",
    "name": "Ahmedfathy",
    "expireDate": "12/25",
    "type": "mastercard",
    "userId": 264,
    "balance": 5,
    "status": "active",
    "createdAt": "2024-12-08T07:59:30.258",
    "updatedAt": "2024-12-08T07:59:30.258"
  },
  {
    "id": 30,
    "bankId": "ef257efe-9b6d-11ef-bb53-2bf5ae5ebe9a",
    "cardNumber": "5342711086892948",
    "cvv": "982",
    "name": "Rehab Attia",
    "expireDate": "11/30",
    "type": "mastercard",
    "userId": 16,
    "balance": 8.71,
    "status": "active",
    "createdAt": "2024-11-05T13:28:43.987",
    "updatedAt": "2024-11-06T11:35:22.711"
  },
  {
    "id": 39,
    "bankId": "ae19c1c2-a464-11ef-9973-93c52b33c5d8",
    "cardNumber": "5342711066406750",
    "cvv": "123",
    "name": "Ahmed ghareb",
    "expireDate": "11/25",
    "type": "mastercard",
    "userId": 56,
    "balance": 20,
    "status": "active",
    "createdAt": "2024-11-30T16:17:06.265",
    "updatedAt": "2024-11-30T17:09:04.277"
  },
  {
    "id": 28,
    "bankId": "c0ddcb4a-9524-11ef-b231-cfb55daf625a",
    "cardNumber": "5342711049266362",
    "cvv": "394",
    "name": "Ahmed Saad",
    "expireDate": "10/30",
    "type": "mastercard",
    "userId": 15,
    "balance": 266,
    "status": "active",
    "createdAt": "2024-10-28T12:05:10.149",
    "updatedAt": "2024-11-06T23:08:16.438"
  },
  {
    "id": 32,
    "bankId": "27dda79c-8b30-11ef-81db-1375765feda0",
    "cardNumber": "5342711010638417",
    "cvv": "763",
    "name": "Dileep Kumar",
    "expireDate": "10/25",
    "type": "mastercard",
    "userId": 37,
    "balance": 5,
    "status": "active",
    "createdAt": "2024-11-13T12:26:05.582",
    "updatedAt": "2024-11-13T12:26:05.582"
  },
  {
    "id": 33,
    "bankId": "205479fc-a600-11ef-8338-a755b8d0b826",
    "cardNumber": "5342711097875213",
    "cvv": "952",
    "name": "Mohamed host",
    "expireDate": "11/25",
    "type": "mastercard",
    "userId": 46,
    "balance": 274,
    "status": "active",
    "createdAt": "2024-11-18T23:13:35.856",
    "updatedAt": "2024-11-18T23:13:35.856"
  },
  {
    "id": 34,
    "bankId": "32863aba-a6dd-11ef-8282-0bda3586f6d2",
    "cardNumber": "5342711038811947",
    "cvv": "013",
    "name": "Ahmed Yehia Kadry",
    "expireDate": "11/25",
    "type": "mastercard",
    "userId": 48,
    "balance": 10,
    "status": "active",
    "createdAt": "2024-11-20T01:17:54.35",
    "updatedAt": "2024-11-20T01:17:54.35"
  },
  {
    "id": 35,
    "bankId": "dc8a439e-6aa6-11ef-9d29-3356d8a1b205",
    "cardNumber": "1234123412341234",
    "cvv": "123",
    "name": "Zeyad Tarek tolan",
    "expireDate": "12/34",
    "type": "mastercard",
    "userId": 44,
    "balance": 561,
    "status": "active",
    "createdAt": "2024-11-20T13:24:48.292",
    "updatedAt": "2024-11-20T13:24:48.292"
  },
  {
    "id": 40,
    "bankId": "b8e9787c-af45-11ef-b72f-4f070af13c07",
    "cardNumber": "5342711047006695",
    "cvv": "137",
    "name": "Hussien Mohamed",
    "expireDate": "11/25",
    "type": "mastercard",
    "userId": 75,
    "balance": 5,
    "status": "active",
    "createdAt": "2024-11-30T18:06:19.179",
    "updatedAt": "2024-11-30T18:06:19.179"
  },
  {
    "id": 3,
    "bankId": "4dac4e3a-16d0-11ef-9d2b-475557a4ec80",
    "cardNumber": "5342711039767437",
    "cvv": "765",
    "name": "Zeyad Tarek tolan",
    "expireDate": "05/30",
    "type": "mastercard",
    "userId": 6,
    "balance": 450,
    "status": "active",
    "createdAt": "2024-10-25T00:47:06.187",
    "updatedAt": "2024-11-26T04:48:29.051"
  },
  {
    "id": 41,
    "bankId": "595650f8-af52-11ef-8e37-a783af2dc127",
    "cardNumber": "5342711057922690",
    "cvv": "461",
    "name": "mahmoud sobhy",
    "expireDate": "11/25",
    "type": "mastercard",
    "userId": 76,
    "balance": 7,
    "status": "active",
    "createdAt": "2024-11-30T19:36:42.77",
    "updatedAt": "2024-11-30T19:36:42.77"
  },
  {
    "id": 42,
    "bankId": "1b4a6cdc-d586-11ee-8a72-575d3041deb3",
    "cardNumber": "1234123412341234",
    "cvv": "123",
    "name": "Hd",
    "expireDate": "01/23",
    "type": "mastercard",
    "userId": 61,
    "balance": 5,
    "status": "active",
    "createdAt": "2024-12-01T22:50:57.147",
    "updatedAt": "2024-12-01T22:50:57.147"
  },
  {
    "id": 43,
    "bankId": "9e9b4174-b27b-11ef-9c7b-3fe4d2419ca9",
    "cardNumber": "5342711081427740",
    "cvv": "682",
    "name": "Abdel Moneim",
    "expireDate": "12/25",
    "type": "mastercard",
    "userId": 167,
    "balance": 5,
    "status": "active",
    "createdAt": "2024-12-04T20:09:29.888",
    "updatedAt": "2024-12-04T20:09:29.888"
  },
  {
    "id": 45,
    "bankId": "1f31ad08-b28d-11ef-a292-8b7c3cb4dcbd",
    "cardNumber": "5342711056959248",
    "cvv": "622",
    "name": "Mohamed Adel Neyazi Elashram",
    "expireDate": "12/25",
    "type": "mastercard",
    "userId": 149,
    "balance": 5,
    "status": "active",
    "createdAt": "2024-12-04T22:14:48.32",
    "updatedAt": "2024-12-04T22:14:48.32"
  },
  {
    "id": 46,
    "bankId": "b2829560-b29f-11ef-b05c-67187a6173d3",
    "cardNumber": "5342711070829518",
    "cvv": "496",
    "name": "Ahmed Tawfik",
    "expireDate": "12/25",
    "type": "mastercard",
    "userId": 211,
    "balance": 5,
    "status": "active",
    "createdAt": "2024-12-05T00:27:49.362",
    "updatedAt": "2024-12-05T00:27:49.362"
  },
  {
    "id": 47,
    "bankId": "90b278b0-b2cc-11ef-881a-3fe17dc07006",
    "cardNumber": "5342711007385550",
    "cvv": "132",
    "name": "Ahmed seragy",
    "expireDate": "12/25",
    "type": "mastercard",
    "userId": 233,
    "balance": 10,
    "status": "active",
    "createdAt": "2024-12-05T05:48:57.992",
    "updatedAt": "2024-12-05T05:48:57.992"
  },
  {
    "id": 48,
    "bankId": "291350da-b2ea-11ef-b909-ebbf0ed5bd23",
    "cardNumber": "5342711024379636",
    "cvv": "984",
    "name": "Talaat abdelhamid",
    "expireDate": "12/25",
    "type": "mastercard",
    "userId": 245,
    "balance": 5,
    "status": "active",
    "createdAt": "2024-12-05T09:21:19.511",
    "updatedAt": "2024-12-05T09:21:19.511"
  },
  {
    "id": 49,
    "bankId": "3ab79ae2-b337-11ef-8a72-f7e0e667f259",
    "cardNumber": "5342711046505713",
    "cvv": "049",
    "name": "Mohammedahmed",
    "expireDate": "12/25",
    "type": "mastercard",
    "userId": 291,
    "balance": 5,
    "status": "active",
    "createdAt": "2024-12-05T18:32:29.097",
    "updatedAt": "2024-12-05T18:32:29.097"
  },
  {
    "id": 51,
    "bankId": "260c433e-b36b-11ef-8723-7744c1e10e85",
    "cardNumber": "5342711020074546",
    "cvv": "998",
    "name": "Shady Ali",
    "expireDate": "12/25",
    "type": "mastercard",
    "userId": 303,
    "balance": 5,
    "status": "active",
    "createdAt": "2024-12-06T00:44:08.201",
    "updatedAt": "2024-12-06T00:44:08.201"
  },
  {
    "id": 52,
    "bankId": "61a3a86e-b3ee-11ef-b79b-9786e8e85dcd",
    "cardNumber": "5342711083752830",
    "cvv": "533",
    "name": "Hossam",
    "expireDate": "12/25",
    "type": "mastercard",
    "userId": 312,
    "balance": 5,
    "status": "active",
    "createdAt": "2024-12-06T16:23:38.358",
    "updatedAt": "2024-12-06T16:23:38.358"
  },
  {
    "id": 54,
    "bankId": "ce2b301a-b3ee-11ef-be2b-6b8e55e032d2",
    "cardNumber": "5342711070307127",
    "cvv": "285",
    "name": "Mohamed Nagy",
    "expireDate": "12/25",
    "type": "mastercard",
    "userId": 328,
    "balance": 10,
    "status": "active",
    "createdAt": "2024-12-06T16:26:31.004",
    "updatedAt": "2024-12-06T16:26:31.004"
  },
  {
    "id": 55,
    "bankId": "2034874e-b3ef-11ef-9e1f-5352b065d9a6",
    "cardNumber": "5342711039966989",
    "cvv": "564",
    "name": "aliriz",
    "expireDate": "12/25",
    "type": "mastercard",
    "userId": 90,
    "balance": 10,
    "status": "active",
    "createdAt": "2024-12-06T16:28:50.04",
    "updatedAt": "2024-12-06T16:28:50.04"
  },
  {
    "id": 57,
    "bankId": "690997c4-b3ff-11ef-be90-0bfb924d0054",
    "cardNumber": "5342711012495832",
    "cvv": "722",
    "name": "Hassan",
    "expireDate": "12/25",
    "type": "mastercard",
    "userId": 333,
    "balance": 5,
    "status": "active",
    "createdAt": "2024-12-06T18:25:35.073",
    "updatedAt": "2024-12-06T18:25:35.073"
  },
  {
    "id": 58,
    "bankId": "a33fbfac-b410-11ef-82cb-9794aabd78af",
    "cardNumber": "5342711010845301",
    "cvv": "865",
    "name": "nasser saleh abdellah",
    "expireDate": "12/25",
    "type": "mastercard",
    "userId": 349,
    "balance": 5,
    "status": "active",
    "createdAt": "2024-12-06T20:28:39.679",
    "updatedAt": "2024-12-06T20:28:39.679"
  },
  {
    "id": 59,
    "bankId": "047a50a0-b43b-11ef-aaf5-af1d17a0947f",
    "cardNumber": "5342711092712783",
    "cvv": "145",
    "name": "Mohamed nour",
    "expireDate": "12/25",
    "type": "mastercard",
    "userId": 309,
    "balance": 315,
    "status": "active",
    "createdAt": "2024-12-07T01:32:05.874",
    "updatedAt": "2025-02-19T18:53:09.212"
  },
  {
    "id": 60,
    "bankId": "00a2f5fa-b480-11ef-8575-0714154ae180",
    "cardNumber": "5342711048871584",
    "cvv": "389",
    "name": "Boula Gergis",
    "expireDate": "12/25",
    "type": "mastercard",
    "userId": 376,
    "balance": 5,
    "status": "active",
    "createdAt": "2024-12-07T09:46:02.666",
    "updatedAt": "2024-12-07T09:46:02.666"
  },
  {
    "id": 69,
    "bankId": "7d79fdb8-b5c4-11ef-a295-0740b42a37ed",
    "cardNumber": "5342711098950783",
    "cvv": "463",
    "name": "Wael Ibrahim",
    "expireDate": "12/25",
    "type": "mastercard",
    "userId": 471,
    "balance": 5,
    "status": "active",
    "createdAt": "2024-12-09T00:28:44.187",
    "updatedAt": "2024-12-09T00:28:44.187"
  },
  {
    "id": 62,
    "bankId": "ae830648-b538-11ef-8426-dbdf66056d81",
    "cardNumber": "5342711061946164",
    "cvv": "715",
    "name": "Ahmed Moheb Mohammed",
    "expireDate": "12/25",
    "type": "mastercard",
    "userId": 350,
    "balance": 5,
    "status": "active",
    "createdAt": "2024-12-08T07:48:15.235",
    "updatedAt": "2024-12-08T07:48:15.235"
  },
  {
    "id": 63,
    "bankId": "0c49062e-b539-11ef-bb1d-d7ad3e0b5c7e",
    "cardNumber": "5342711019859675",
    "cvv": "777",
    "name": "Mr zizo",
    "expireDate": "12/25",
    "type": "mastercard",
    "userId": 421,
    "balance": 5,
    "status": "active",
    "createdAt": "2024-12-08T07:50:39.866",
    "updatedAt": "2024-12-08T07:50:39.866"
  },
  {
    "id": 67,
    "bankId": "99770fac-b564-11ef-99d4-ebb5b4348166",
    "cardNumber": "5342711039512544",
    "cvv": "524",
    "name": "MOHAMED TAREK ALY",
    "expireDate": "12/25",
    "type": "mastercard",
    "userId": 396,
    "balance": 20,
    "status": "active",
    "createdAt": "2024-12-08T13:02:14.503",
    "updatedAt": "2024-12-08T13:02:14.503"
  },
  {
    "id": 31,
    "bankId": "b9b94126-9f3a-11ef-b23f-b390d804ddf6",
    "cardNumber": "5342711090252063",
    "cvv": "957",
    "name": "Ahmed Hagag",
    "expireDate": "11/25",
    "type": "mastercard",
    "userId": 32,
    "balance": 25,
    "status": "active",
    "createdAt": "2024-11-10T08:07:09.009",
    "updatedAt": "2024-12-13T00:30:05.679"
  },
  {
    "id": 71,
    "bankId": "70806012-b618-11ef-83cd-abfdcac734b2",
    "cardNumber": "5342711011518444",
    "cvv": "933",
    "name": "Mostafa Hasan Mahmoud Elsayed Elnahhas",
    "expireDate": "12/25",
    "type": "mastercard",
    "userId": 483,
    "balance": 5,
    "status": "active",
    "createdAt": "2024-12-09T10:29:37.157",
    "updatedAt": "2024-12-09T10:29:37.157"
  },
  {
    "id": 56,
    "bankId": "725090ea-b3ef-11ef-8afa-232595173849",
    "cardNumber": "5342711072909854",
    "cvv": "168",
    "name": "Ahmed Housam",
    "expireDate": "12/25",
    "type": "mastercard",
    "userId": 339,
    "balance": 99,
    "status": "active",
    "createdAt": "2024-12-06T16:31:05.283",
    "updatedAt": "2025-02-03T19:17:07.511"
  },
  {
    "id": 66,
    "bankId": "88751982-8612-11ef-9dcf-0faa1e0607a3",
    "cardNumber": "5342711030053829",
    "cvv": "606",
    "name": "CHERIF ABOUL KHAIR",
    "expireDate": "10/25",
    "type": "mastercard",
    "userId": 429,
    "balance": 95,
    "status": "active",
    "createdAt": "2024-12-08T12:00:14.255",
    "updatedAt": "2025-02-12T20:24:59.07"
  },
  {
    "id": 36,
    "bankId": "438e3c1e-a3a3-11ef-9f7a-9b3ad7c789ed",
    "cardNumber": "5342711075348670",
    "cvv": "341",
    "name": "Ahmed Saad",
    "expireDate": "11/25",
    "type": "mastercard",
    "userId": 53,
    "balance": 189,
    "status": "active",
    "createdAt": "2024-11-25T14:03:05.283",
    "updatedAt": "2025-01-07T10:44:53.443"
  },
  {
    "id": 50,
    "bankId": "60b24406-b35d-11ef-9d40-5fed3513af4b",
    "cardNumber": "5342711026543106",
    "cvv": "927",
    "name": "NOURELDINK",
    "expireDate": "12/30",
    "type": "mastercard",
    "userId": 299,
    "balance": 67,
    "status": "active",
    "createdAt": "2024-12-05T23:05:53.267",
    "updatedAt": "2025-02-12T10:44:15.571"
  },
  {
    "id": 61,
    "bankId": "12073132-b497-11ef-9da1-0b2b043392b5",
    "cardNumber": "5342711044998787",
    "cvv": "577",
    "name": "salsabil ahmed",
    "expireDate": "12/30",
    "type": "mastercard",
    "userId": 80,
    "balance": 80,
    "status": "active",
    "createdAt": "2024-12-07T12:31:38.378",
    "updatedAt": "2025-02-22T19:16:02.468"
  },
  {
    "id": 68,
    "bankId": "11a2172c-b57b-11ef-b8ca-63a41f42b09c",
    "cardNumber": "5342711057623280",
    "cvv": "612",
    "name": "Seraj Saleh",
    "expireDate": "12/25",
    "type": "mastercard",
    "userId": 259,
    "balance": 787,
    "status": "active",
    "createdAt": "2024-12-08T15:43:08.235",
    "updatedAt": "2024-12-25T13:44:44.901"
  },
  {
    "id": 37,
    "bankId": "d84e11d0-ae66-11ef-8caa-ffa4d4da9265",
    "cardNumber": "5342711039036502",
    "cvv": "642",
    "name": "Mohamed Maged Fathi",
    "expireDate": "11/25",
    "type": "mastercard",
    "userId": 67,
    "balance": 24,
    "status": "active",
    "createdAt": "2024-11-29T15:30:42.004",
    "updatedAt": "2025-01-31T05:42:11.541"
  },
  {
    "id": 70,
    "bankId": "49b6d4a2-b618-11ef-b8bb-dfae208f9657",
    "cardNumber": "5342711026318798",
    "cvv": "912",
    "name": "Mohammed Wagih",
    "expireDate": "12/25",
    "type": "mastercard",
    "userId": 477,
    "balance": 223,
    "status": "active",
    "createdAt": "2024-12-09T10:28:37.034",
    "updatedAt": "2025-02-06T05:40:40.319"
  },
  {
    "id": 64,
    "bankId": "412a4650-b539-11ef-9d39-3306fbff5beb",
    "cardNumber": "5342711092245248",
    "cvv": "608",
    "name": "George sherif",
    "expireDate": "12/25",
    "type": "mastercard",
    "userId": 402,
    "balance": 101,
    "status": "active",
    "createdAt": "2024-12-08T07:52:32.891",
    "updatedAt": "2025-02-02T21:45:21.41"
  },
  {
    "id": 53,
    "bankId": "99d1498a-b3ee-11ef-84fe-976834a6cdfe",
    "cardNumber": "5342711004966022",
    "cvv": "102",
    "name": "selim badwy",
    "expireDate": "12/25",
    "type": "mastercard",
    "userId": 318,
    "balance": 25,
    "status": "active",
    "createdAt": "2024-12-06T16:25:46.079",
    "updatedAt": "2025-01-25T03:05:49.818"
  },
  {
    "id": 44,
    "bankId": "eb9bc72e-b27f-11ef-b30f-4f2b708fe856",
    "cardNumber": "5342711012327043",
    "cvv": "894",
    "name": "abdallaj",
    "expireDate": "12/25",
    "type": "mastercard",
    "userId": 180,
    "balance": 92,
    "status": "active",
    "createdAt": "2024-12-04T20:40:20.485",
    "updatedAt": "2025-02-24T21:33:24.265"
  },
  {
    "id": 73,
    "bankId": "40ca138e-b647-11ef-85d3-5ba02e6222af",
    "cardNumber": "5342711020306476",
    "cvv": "888",
    "name": "Elhassan Orabi",
    "expireDate": "12/25",
    "type": "mastercard",
    "userId": 501,
    "balance": 5,
    "status": "active",
    "createdAt": "2024-12-09T16:04:48.241",
    "updatedAt": "2024-12-09T16:04:48.241"
  },
  {
    "id": 72,
    "bankId": "b7561cce-b646-11ef-a8f7-43216e18e4ad",
    "cardNumber": "5342711039891187",
    "cvv": "451",
    "name": "Hossam Ahmed ahmed",
    "expireDate": "12/25",
    "type": "mastercard",
    "userId": 482,
    "balance": 10,
    "status": "active",
    "createdAt": "2024-12-09T16:00:57.541",
    "updatedAt": "2024-12-09T20:29:49.529"
  },
  {
    "id": 74,
    "bankId": "78988262-b66c-11ef-b609-bb6cb33df945",
    "cardNumber": "5342711049238932",
    "cvv": "508",
    "name": "Moaz Elzamamry",
    "expireDate": "12/25",
    "type": "mastercard",
    "userId": 512,
    "balance": 10,
    "status": "active",
    "createdAt": "2024-12-09T20:31:04.145",
    "updatedAt": "2024-12-09T20:31:04.145"
  },
  {
    "id": 76,
    "bankId": "10fa4616-b6ff-11ef-b0b8-13df859f432f",
    "cardNumber": "5342711090809540",
    "cvv": "556",
    "name": "Ahmed Ashraf Abdel Sabour",
    "expireDate": "12/25",
    "type": "mastercard",
    "userId": 537,
    "balance": 8,
    "status": "active",
    "createdAt": "2024-12-10T14:00:30.349",
    "updatedAt": "2024-12-10T14:00:30.349"
  },
  {
    "id": 78,
    "bankId": "44535356-b7c5-11ef-870f-0798a494ea59",
    "cardNumber": "5342711046426233",
    "cvv": "701",
    "name": "ESLAM MAGDY RAMADAN ABDELAAL",
    "expireDate": "12/25",
    "type": "mastercard",
    "userId": 549,
    "balance": 5,
    "status": "active",
    "createdAt": "2024-12-11T13:39:13.579",
    "updatedAt": "2024-12-11T13:39:13.579"
  },
  {
    "id": 79,
    "bankId": "13297160-b7c6-11ef-bbbc-1fb829296e5f",
    "cardNumber": "5342711056597725",
    "cvv": "351",
    "name": "AHMED ATTIA",
    "expireDate": "12/25",
    "type": "mastercard",
    "userId": 547,
    "balance": 5,
    "status": "active",
    "createdAt": "2024-12-11T13:45:09.305",
    "updatedAt": "2024-12-11T13:45:09.305"
  },
  {
    "id": 80,
    "bankId": "96bc5006-b7d5-11ef-81d2-37342670c9cc",
    "cardNumber": "5342711022492803",
    "cvv": "806",
    "name": "Karim galal",
    "expireDate": "12/25",
    "type": "mastercard",
    "userId": 559,
    "balance": 5,
    "status": "active",
    "createdAt": "2024-12-11T15:36:05.393",
    "updatedAt": "2024-12-11T15:36:05.393"
  },
  {
    "id": 81,
    "bankId": "6960fe68-b7ee-11ef-9a6f-6f546c5dbfe0",
    "cardNumber": "5342711048106957",
    "cvv": "667",
    "name": "hamza sadek",
    "expireDate": "12/25",
    "type": "mastercard",
    "userId": 550,
    "balance": 5,
    "status": "active",
    "createdAt": "2024-12-11T18:33:52.689",
    "updatedAt": "2024-12-11T18:33:52.689"
  },
  {
    "id": 82,
    "bankId": "cf13c64c-b7fc-11ef-b8c2-0fa57245ad12",
    "cardNumber": "5342711080097478",
    "cvv": "772",
    "name": "Zeyad Tolan",
    "expireDate": "12/25",
    "type": "mastercard",
    "userId": 562,
    "balance": 100,
    "status": "active",
    "createdAt": "2024-12-11T20:23:21.09",
    "updatedAt": "2024-12-11T20:23:21.09"
  },
  {
    "id": 85,
    "bankId": "a55850d2-b943-11ef-b063-cfc698092d6d",
    "cardNumber": "5342711038230791",
    "cvv": "530",
    "name": "Mohamed Ashra Mohamed kamalf",
    "expireDate": "12/25",
    "type": "mastercard",
    "userId": 585,
    "balance": 5,
    "status": "active",
    "createdAt": "2024-12-13T11:16:29.779",
    "updatedAt": "2024-12-13T11:16:29.779"
  },
  {
    "id": 86,
    "bankId": "c236aa78-b943-11ef-a640-37123e420d58",
    "cardNumber": "5342711060876370",
    "cvv": "558",
    "name": "Mohamed Gaballa",
    "expireDate": "12/25",
    "type": "mastercard",
    "userId": 588,
    "balance": 20,
    "status": "active",
    "createdAt": "2024-12-13T11:17:11.457",
    "updatedAt": "2024-12-13T11:17:11.457"
  },
  {
    "id": 87,
    "bankId": "54df2c66-b948-11ef-96ae-2fbbdd17e2c7",
    "cardNumber": "5342711087783799",
    "cvv": "849",
    "name": "ahmed yahya",
    "expireDate": "12/25",
    "type": "mastercard",
    "userId": 589,
    "balance": 5,
    "status": "active",
    "createdAt": "2024-12-13T11:50:13.182",
    "updatedAt": "2024-12-13T11:50:13.182"
  },
  {
    "id": 89,
    "bankId": "921748f8-b974-11ef-8697-07dedc13db6c",
    "cardNumber": "5342711006511883",
    "cvv": "579",
    "name": "Mohamed ashraf mohamed",
    "expireDate": "12/25",
    "type": "mastercard",
    "userId": 586,
    "balance": 5,
    "status": "active",
    "createdAt": "2024-12-13T17:07:06.008",
    "updatedAt": "2024-12-13T17:07:06.008"
  },
  {
    "id": 108,
    "bankId": "07c73d10-bf88-11ef-80a1-1fb606e07c20",
    "cardNumber": "5342711080980566",
    "cvv": "637",
    "name": "Mahmoud",
    "expireDate": "12/25",
    "type": "mastercard",
    "userId": 359,
    "balance": 7,
    "status": "active",
    "createdAt": "2024-12-21T10:41:04.025",
    "updatedAt": "2024-12-21T10:41:04.025"
  },
  {
    "id": 91,
    "bankId": "76292ec8-b99b-11ef-b6c4-6f242259401e",
    "cardNumber": "5342711023687609",
    "cvv": "594",
    "name": "AMR MAHMOUD",
    "expireDate": "12/25",
    "type": "mastercard",
    "userId": 252,
    "balance": 5,
    "status": "active",
    "createdAt": "2024-12-13T21:45:17.283",
    "updatedAt": "2024-12-13T21:45:17.283"
  },
  {
    "id": 109,
    "bankId": "21b71bb4-bf88-11ef-ae6a-a7a24dd94e6d",
    "cardNumber": "5342711096583073",
    "cvv": "608",
    "name": "Osama hany",
    "expireDate": "12/25",
    "type": "mastercard",
    "userId": 765,
    "balance": 5,
    "status": "active",
    "createdAt": "2024-12-21T10:41:47.069",
    "updatedAt": "2024-12-21T10:41:47.069"
  },
  {
    "id": 94,
    "bankId": "84de61d4-b4bb-11ef-9648-a7384b043f72",
    "cardNumber": "5342711001411972",
    "cvv": "520",
    "name": "moafak",
    "expireDate": "12/30",
    "type": "mastercard",
    "userId": 643,
    "balance": 99.87,
    "status": "active",
    "createdAt": "2024-12-15T15:59:47.016",
    "updatedAt": "2024-12-15T15:59:47.016"
  },
  {
    "id": 95,
    "bankId": "fb255d78-bb43-11ef-9912-43c91cf0f562",
    "cardNumber": "5342711016021485",
    "cvv": "985",
    "name": "Mohamed Elaraby",
    "expireDate": "12/25",
    "type": "mastercard",
    "userId": 655,
    "balance": 6,
    "status": "active",
    "createdAt": "2024-12-16T00:24:04.602",
    "updatedAt": "2024-12-16T00:24:04.602"
  },
  {
    "id": 102,
    "bankId": "c688289a-be0c-11ef-b01b-33a6583a8ff9",
    "cardNumber": "5342711089680266",
    "cvv": "116",
    "name": "Muaz Ahmed Nasr",
    "expireDate": "12/25",
    "type": "mastercard",
    "userId": 682,
    "balance": 430,
    "status": "active",
    "createdAt": "2024-12-19T13:26:27.112",
    "updatedAt": "2025-02-22T19:15:31.31"
  },
  {
    "id": 114,
    "bankId": "ff7bcc1c-c0b7-11ef-964c-87a007b443b8",
    "cardNumber": "5342711012123251",
    "cvv": "656",
    "name": "AHMED MOHAMED",
    "expireDate": "12/25",
    "type": "mastercard",
    "userId": 807,
    "balance": 5,
    "status": "active",
    "createdAt": "2024-12-22T22:56:54.32",
    "updatedAt": "2024-12-22T22:56:54.32"
  },
  {
    "id": 77,
    "bankId": "b5aba24a-b704-11ef-a223-e371c59600cc",
    "cardNumber": "5342711092798436",
    "cvv": "960",
    "name": "Negm Eldin",
    "expireDate": "12/25",
    "type": "mastercard",
    "userId": 340,
    "balance": 62,
    "status": "active",
    "createdAt": "2024-12-10T14:40:59.891",
    "updatedAt": "2024-12-17T16:20:44.492"
  },
  {
    "id": 98,
    "bankId": "41da7804-bca5-11ef-b7f3-ff1eae5596b7",
    "cardNumber": "5342711017680974",
    "cvv": "548",
    "name": "Abdelrahman Khattab",
    "expireDate": "12/25",
    "type": "mastercard",
    "userId": 692,
    "balance": 5,
    "status": "active",
    "createdAt": "2024-12-17T18:32:43.947",
    "updatedAt": "2024-12-17T18:32:43.947"
  },
  {
    "id": 90,
    "bankId": "057e0c3c-b975-11ef-9332-b3a12224581c",
    "cardNumber": "5342711001334794",
    "cvv": "388",
    "name": "Ahmed sobhy",
    "expireDate": "12/25",
    "type": "mastercard",
    "userId": 593,
    "balance": 105,
    "status": "active",
    "createdAt": "2024-12-13T17:10:07.442",
    "updatedAt": "2025-01-19T15:06:02.776"
  },
  {
    "id": 116,
    "bankId": "32e601a6-c173-11ef-950e-ebf3b14a0526",
    "cardNumber": "5342711068097060",
    "cvv": "199",
    "name": "Eslam Barakat",
    "expireDate": "12/25",
    "type": "mastercard",
    "userId": 57,
    "balance": 5,
    "status": "active",
    "createdAt": "2024-12-23T21:16:59.646",
    "updatedAt": "2024-12-23T21:16:59.646"
  },
  {
    "id": 101,
    "bankId": "24d8c92a-bdd8-11ef-a890-cbe205058a98",
    "cardNumber": "5342711002729984",
    "cvv": "888",
    "name": "Khaled Gamal Elish",
    "expireDate": "12/25",
    "type": "mastercard",
    "userId": 713,
    "balance": 5,
    "status": "active",
    "createdAt": "2024-12-19T07:09:31.065",
    "updatedAt": "2024-12-19T07:09:31.065"
  },
  {
    "id": 103,
    "bankId": "a4ca49b8-be16-11ef-8fa5-bfc8c398d6b8",
    "cardNumber": "5342711054192388",
    "cvv": "648",
    "name": "Moaz",
    "expireDate": "12/25",
    "type": "mastercard",
    "userId": 556,
    "balance": 80,
    "status": "active",
    "createdAt": "2024-12-19T14:37:11.19",
    "updatedAt": "2024-12-20T07:14:03.509"
  },
  {
    "id": 107,
    "bankId": "e092bbf2-bf87-11ef-8583-5f08e5a12c0d",
    "cardNumber": "5342711052124136",
    "cvv": "656",
    "name": "Hussein Tarek",
    "expireDate": "12/25",
    "type": "mastercard",
    "userId": 753,
    "balance": 25,
    "status": "active",
    "createdAt": "2024-12-21T10:40:00.704",
    "updatedAt": "2025-02-20T22:32:46.892"
  },
  {
    "id": 84,
    "bankId": "211d1ffc-b8d8-11ef-b50e-affe4fb54bd7",
    "cardNumber": "5342711039317357",
    "cvv": "641",
    "name": "Islam Ahmed Mohamed",
    "expireDate": "12/30",
    "type": "mastercard",
    "userId": 408,
    "balance": 111,
    "status": "active",
    "createdAt": "2024-12-12T22:27:14.414",
    "updatedAt": "2025-02-01T18:40:16.201"
  },
  {
    "id": 106,
    "bankId": "f7f1e334-bee9-11ef-bcfb-c7790af773a1",
    "cardNumber": "5342711000479731",
    "cvv": "252",
    "name": "omar elshafey",
    "expireDate": "12/25",
    "type": "mastercard",
    "userId": 79,
    "balance": 27,
    "status": "active",
    "createdAt": "2024-12-20T15:49:36.237",
    "updatedAt": "2024-12-27T19:06:59.6"
  },
  {
    "id": 112,
    "bankId": "5532eb4e-c073-11ef-b401-6ffdf26fe0ff",
    "cardNumber": "5342711089635195",
    "cvv": "942",
    "name": "Kareem",
    "expireDate": "12/25",
    "type": "mastercard",
    "userId": 799,
    "balance": 5,
    "status": "active",
    "createdAt": "2024-12-22T14:45:39.683",
    "updatedAt": "2024-12-22T14:45:39.683"
  },
  {
    "id": 115,
    "bankId": "f51e6d04-c127-11ef-9741-e7d01d017f9e",
    "cardNumber": "5342711044901849",
    "cvv": "135",
    "name": "Islam Maged",
    "expireDate": "12/25",
    "type": "mastercard",
    "userId": 816,
    "balance": 5,
    "status": "active",
    "createdAt": "2024-12-23T12:22:57.569",
    "updatedAt": "2024-12-23T12:22:57.569"
  },
  {
    "id": 113,
    "bankId": "d118b014-c09f-11ef-9bdc-1f911d02f593",
    "cardNumber": "5342711016707406",
    "cvv": "314",
    "name": "Ahmed Khaled",
    "expireDate": "12/25",
    "type": "mastercard",
    "userId": 801,
    "balance": 22,
    "status": "active",
    "createdAt": "2024-12-22T20:04:13.146",
    "updatedAt": "2024-12-23T13:31:20.904"
  },
  {
    "id": 104,
    "bankId": "541f0bde-bea2-11ef-abe4-2b087b9bf712",
    "cardNumber": "5342711082704576",
    "cvv": "795",
    "name": "Amr Raafat",
    "expireDate": "12/25",
    "type": "mastercard",
    "userId": 726,
    "balance": 10,
    "status": "active",
    "createdAt": "2024-12-20T07:17:10.849",
    "updatedAt": "2025-02-06T13:32:01.418"
  },
  {
    "id": 75,
    "bankId": "95e7c6ca-b66c-11ef-80c1-a3bedff79711",
    "cardNumber": "5342711099722546",
    "cvv": "766",
    "name": "Khaled Osama",
    "expireDate": "12/25",
    "type": "mastercard",
    "userId": 517,
    "balance": 49,
    "status": "active",
    "createdAt": "2024-12-09T20:31:55.035",
    "updatedAt": "2025-01-21T17:47:41"
  },
  {
    "id": 117,
    "bankId": "57d74280-c200-11ef-82c7-83f2f903a7f2",
    "cardNumber": "5342711010970851",
    "cvv": "961",
    "name": "Hossam Mohsen Ibrahim",
    "expireDate": "12/25",
    "type": "mastercard",
    "userId": 453,
    "balance": 5,
    "status": "active",
    "createdAt": "2024-12-24T14:07:21.492",
    "updatedAt": "2024-12-24T14:07:21.492"
  },
  {
    "id": 118,
    "bankId": "79d1784c-c200-11ef-8dbb-c7857791578f",
    "cardNumber": "5342711028605978",
    "cvv": "981",
    "name": "Salma Hesham",
    "expireDate": "12/25",
    "type": "mastercard",
    "userId": 843,
    "balance": 20,
    "status": "active",
    "createdAt": "2024-12-24T14:08:21.573",
    "updatedAt": "2024-12-24T14:08:21.573"
  },
  {
    "id": 119,
    "bankId": "16026276-c206-11ef-9f37-dff9b045c1e7",
    "cardNumber": "5342711000466753",
    "cvv": "433",
    "name": "Mohamed Ragheb",
    "expireDate": "12/25",
    "type": "mastercard",
    "userId": 841,
    "balance": 5,
    "status": "active",
    "createdAt": "2024-12-24T14:48:27.677",
    "updatedAt": "2024-12-24T14:48:27.677"
  },
  {
    "id": 120,
    "bankId": "85931be2-c20d-11ef-91db-372b584800ab",
    "cardNumber": "5342711062340409",
    "cvv": "315",
    "name": "MOHAMED ASHRAF",
    "expireDate": "12/25",
    "type": "mastercard",
    "userId": 845,
    "balance": 5,
    "status": "active",
    "createdAt": "2024-12-24T15:41:41.897",
    "updatedAt": "2024-12-24T15:41:41.897"
  },
  {
    "id": 83,
    "bankId": "874e04a8-b851-11ef-b0ff-ffd2a5776d77",
    "cardNumber": "5342711065894030",
    "cvv": "603",
    "name": "Mahmoud",
    "expireDate": "12/25",
    "type": "mastercard",
    "userId": 294,
    "balance": 65,
    "status": "active",
    "createdAt": "2024-12-12T06:23:39.742",
    "updatedAt": "2025-01-05T13:22:04.945"
  },
  {
    "id": 100,
    "bankId": "5ce4da30-bd87-11ef-a96c-e3c2ff723eab",
    "cardNumber": "5342711041422666",
    "cvv": "840",
    "name": "mahmoudabood",
    "expireDate": "12/25",
    "type": "mastercard",
    "userId": 707,
    "balance": 93,
    "status": "active",
    "createdAt": "2024-12-18T21:31:14.153",
    "updatedAt": "2025-01-11T15:57:09.438"
  },
  {
    "id": 110,
    "bankId": "f52ca12a-bf9d-11ef-bb8e-3ba50b7ab196",
    "cardNumber": "5342711009334622",
    "cvv": "007",
    "name": "moslem nabil",
    "expireDate": "12/25",
    "type": "mastercard",
    "userId": 348,
    "balance": 51,
    "status": "active",
    "createdAt": "2024-12-21T13:18:06.09",
    "updatedAt": "2025-02-14T19:25:21.616"
  },
  {
    "id": 99,
    "bankId": "ee2e04d6-bd2c-11ef-ac91-47f7a1608216",
    "cardNumber": "5342711055882185",
    "cvv": "732",
    "name": "ahmedsamy",
    "expireDate": "12/25",
    "type": "mastercard",
    "userId": 697,
    "balance": 408,
    "status": "active",
    "createdAt": "2024-12-18T10:43:57.299",
    "updatedAt": "2025-02-06T05:39:39.11"
  },
  {
    "id": 92,
    "bankId": "ad549916-ba39-11ef-8b66-bb57d08a8f39",
    "cardNumber": "5342711026224749",
    "cvv": "432",
    "name": "aymanabubakr",
    "expireDate": "12/25",
    "type": "mastercard",
    "userId": 611,
    "balance": 20,
    "status": "active",
    "createdAt": "2024-12-14T16:37:52.44",
    "updatedAt": "2025-02-28T04:14:16.02"
  },
  {
    "id": 88,
    "bankId": "fd75ce2c-b973-11ef-931d-f7f01c5260f0",
    "cardNumber": "5342711086363395",
    "cvv": "432",
    "name": "Abdelrhman ali",
    "expireDate": "12/25",
    "type": "mastercard",
    "userId": 578,
    "balance": 15,
    "status": "active",
    "createdAt": "2024-12-13T17:02:37.477",
    "updatedAt": "2025-02-04T18:32:33.776"
  },
  {
    "id": 96,
    "bankId": "faf09488-bba4-11ef-96d0-078f68df1f75",
    "cardNumber": "5342711048536567",
    "cvv": "653",
    "name": "Abdallah sakr",
    "expireDate": "12/25",
    "type": "mastercard",
    "userId": 574,
    "balance": 267,
    "status": "active",
    "createdAt": "2024-12-16T11:58:17.818",
    "updatedAt": "2025-02-27T06:43:04.626"
  },
  {
    "id": 97,
    "bankId": "de7f956e-bc90-11ef-80cc-0b40b1bb221e",
    "cardNumber": "5342711014947830",
    "cvv": "539",
    "name": "Mohamed Shehata",
    "expireDate": "12/25",
    "type": "mastercard",
    "userId": 584,
    "balance": 10,
    "status": "active",
    "createdAt": "2024-12-17T16:07:33.033",
    "updatedAt": "2025-02-27T09:11:09.816"
  },
  {
    "id": 93,
    "bankId": "df08ea98-ba39-11ef-8f76-03de2bbced19",
    "cardNumber": "5342711089351223",
    "cvv": "474",
    "name": "Hossam Mohamed Rabie",
    "expireDate": "12/25",
    "type": "mastercard",
    "userId": 614,
    "balance": 16,
    "status": "active",
    "createdAt": "2024-12-14T16:39:14.901",
    "updatedAt": "2025-02-08T18:40:11.438"
  },
  {
    "id": 111,
    "bankId": "ba82d0d0-c065-11ef-852a-2f7cf7fc965e",
    "cardNumber": "5342711099536326",
    "cvv": "038",
    "name": "AhmedGommaa",
    "expireDate": "12/25",
    "type": "mastercard",
    "userId": 796,
    "balance": 41,
    "status": "active",
    "createdAt": "2024-12-22T13:08:03.984",
    "updatedAt": "2025-02-10T20:37:00.227"
  },
  {
    "id": 105,
    "bankId": "55c3f12e-becb-11ef-ac09-7b5d3ef49085",
    "cardNumber": "5342711026248904",
    "cvv": "268",
    "name": "Ammar Elbedweihy",
    "expireDate": "12/25",
    "type": "mastercard",
    "userId": 737,
    "balance": 105,
    "status": "active",
    "createdAt": "2024-12-20T12:10:19.198",
    "updatedAt": "2025-02-28T04:13:22.782"
  },
  {
    "id": 121,
    "bankId": "f28d4344-c22b-11ef-9ae5-43a5bde81f14",
    "cardNumber": "5342711019469137",
    "cvv": "236",
    "name": "Mohamed Elmakas",
    "expireDate": "12/25",
    "type": "mastercard",
    "userId": 850,
    "balance": 72,
    "status": "active",
    "createdAt": "2024-12-24T19:21:43.139",
    "updatedAt": "2024-12-24T19:39:26.769"
  },
  {
    "id": 124,
    "bankId": "97fe3c88-c2cd-11ef-abf9-2bae83f4c222",
    "cardNumber": "5342711058001643",
    "cvv": "318",
    "name": "AHMED SALAMA HASANY BASHIR",
    "expireDate": "12/25",
    "type": "mastercard",
    "userId": 832,
    "balance": 10,
    "status": "active",
    "createdAt": "2024-12-25T14:36:39.076",
    "updatedAt": "2024-12-25T20:05:26.054"
  },
  {
    "id": 128,
    "bankId": "ad5c6430-c357-11ef-9b0f-8f7f290f4ed2",
    "cardNumber": "5342711019272051",
    "cvv": "358",
    "name": "Mohamed Talaat",
    "expireDate": "12/25",
    "type": "mastercard",
    "userId": 885,
    "balance": 10,
    "status": "active",
    "createdAt": "2024-12-26T07:04:59.071",
    "updatedAt": "2024-12-26T07:04:59.071"
  },
  {
    "id": 132,
    "bankId": "292519a8-c485-11ef-a366-fbe54c23a85f",
    "cardNumber": "5342711012653679",
    "cvv": "422",
    "name": "Mahmoud Magdy Hemdan",
    "expireDate": "12/25",
    "type": "mastercard",
    "userId": 919,
    "balance": 5,
    "status": "active",
    "createdAt": "2024-12-27T19:03:06.684",
    "updatedAt": "2024-12-27T19:03:06.684"
  },
  {
    "id": 134,
    "bankId": "875fbd70-c485-11ef-b963-83ff8f4b140c",
    "cardNumber": "5342711010943700",
    "cvv": "166",
    "name": "Ahmed Housam",
    "expireDate": "12/25",
    "type": "mastercard",
    "userId": 782,
    "balance": 10,
    "status": "active",
    "createdAt": "2024-12-27T19:05:49.266",
    "updatedAt": "2024-12-28T01:03:50.705"
  },
  {
    "id": 125,
    "bankId": "a032fffa-c2d3-11ef-87ca-db8a928473fa",
    "cardNumber": "5342711043249091",
    "cvv": "881",
    "name": "Anas Omar",
    "expireDate": "12/25",
    "type": "mastercard",
    "userId": 853,
    "balance": 56,
    "status": "active",
    "createdAt": "2024-12-25T15:19:45.397",
    "updatedAt": "2024-12-28T17:46:41.826"
  },
  {
    "id": 136,
    "bankId": "87890512-c544-11ef-98ea-77882159547e",
    "cardNumber": "5342711042437325",
    "cvv": "175",
    "name": "Mostafa Mohamed",
    "expireDate": "12/25",
    "type": "mastercard",
    "userId": 947,
    "balance": 5,
    "status": "active",
    "createdAt": "2024-12-28T17:52:59.782",
    "updatedAt": "2024-12-28T17:52:59.782"
  },
  {
    "id": 123,
    "bankId": "f26c363a-c2c2-11ef-a345-ef2f695b1310",
    "cardNumber": "5342711085604229",
    "cvv": "269",
    "name": "Abdelrhman",
    "expireDate": "12/25",
    "type": "mastercard",
    "userId": 423,
    "balance": 10,
    "status": "active",
    "createdAt": "2024-12-25T13:20:44.726",
    "updatedAt": "2024-12-29T01:01:52.509"
  },
  {
    "id": 138,
    "bankId": "a5978982-c622-11ef-8ef7-0796695eafc8",
    "cardNumber": "5342711024413112",
    "cvv": "509",
    "name": "Abdelrahman Khamis",
    "expireDate": "12/25",
    "type": "mastercard",
    "userId": 882,
    "balance": 10,
    "status": "active",
    "createdAt": "2024-12-29T20:22:56.807",
    "updatedAt": "2024-12-29T20:22:56.807"
  },
  {
    "id": 139,
    "bankId": "bc81dec2-c622-11ef-a5c6-9f6bf740cac0",
    "cardNumber": "5342711006470130",
    "cvv": "426",
    "name": "Mohamed Ghorayeb",
    "expireDate": "12/25",
    "type": "mastercard",
    "userId": 985,
    "balance": 5,
    "status": "active",
    "createdAt": "2024-12-29T20:23:34.23",
    "updatedAt": "2024-12-29T20:23:34.23"
  },
  {
    "id": 144,
    "bankId": "3d3d4744-c7be-11ef-b1f9-cb5e15a1f765",
    "cardNumber": "5342711030847386",
    "cvv": "809",
    "name": "mohamed Elzahed",
    "expireDate": "12/25",
    "type": "mastercard",
    "userId": 869,
    "balance": 5,
    "status": "active",
    "createdAt": "2024-12-31T21:29:40.977",
    "updatedAt": "2024-12-31T21:29:40.977"
  },
  {
    "id": 140,
    "bankId": "fdeaceae-c628-11ef-a786-8b98f7dcb417",
    "cardNumber": "5342711069536264",
    "cvv": "402",
    "name": "Ahmed",
    "expireDate": "12/25",
    "type": "mastercard",
    "userId": 956,
    "balance": 65,
    "status": "active",
    "createdAt": "2024-12-29T21:08:25.528",
    "updatedAt": "2025-01-01T12:02:05.381"
  },
  {
    "id": 147,
    "bankId": "e58dbc3a-c868-11ef-b002-c3854a9844b0",
    "cardNumber": "5342711008012039",
    "cvv": "114",
    "name": "mohamed ali",
    "expireDate": "01/26",
    "type": "mastercard",
    "userId": 1041,
    "balance": 5,
    "status": "active",
    "createdAt": "2025-01-01T17:51:32.488",
    "updatedAt": "2025-01-01T17:51:32.488"
  },
  {
    "id": 149,
    "bankId": "92b165d0-c88a-11ef-af29-c367987cab6e",
    "cardNumber": "5342711069346193",
    "cvv": "586",
    "name": "Badri Abdul Shafi Abdul Halim",
    "expireDate": "01/26",
    "type": "mastercard",
    "userId": 1053,
    "balance": 5,
    "status": "active",
    "createdAt": "2025-01-01T21:51:53.814",
    "updatedAt": "2025-01-01T21:51:53.814"
  },
  {
    "id": 151,
    "bankId": "6bd583b6-c924-11ef-8fd1-9f5f971831c2",
    "cardNumber": "5342711068776507",
    "cvv": "955",
    "name": "Ahmed osama",
    "expireDate": "01/26",
    "type": "mastercard",
    "userId": 1021,
    "balance": 20,
    "status": "active",
    "createdAt": "2025-01-02T16:13:14.702",
    "updatedAt": "2025-01-02T16:13:14.702"
  },
  {
    "id": 167,
    "bankId": "c1e129be-d729-11ef-b58d-bbf441b1179e",
    "cardNumber": "5342711018948982",
    "cvv": "978",
    "name": "Rafat Mohamed",
    "expireDate": "02/26",
    "type": "mastercard",
    "userId": 1096,
    "balance": 50,
    "status": "active",
    "createdAt": "2025-01-20T12:26:45.192",
    "updatedAt": "2025-02-24T19:44:30.961"
  },
  {
    "id": 130,
    "bankId": "9bbda2ec-c3d0-11ef-b7ce-aff5ceb28565",
    "cardNumber": "5342711027487428",
    "cvv": "926",
    "name": "Ayman Mahdy",
    "expireDate": "12/25",
    "type": "mastercard",
    "userId": 901,
    "balance": 15,
    "status": "active",
    "createdAt": "2024-12-26T21:30:44.538",
    "updatedAt": "2025-01-11T15:53:54.242"
  },
  {
    "id": 156,
    "bankId": "91698a26-cc55-11ef-bbe6-435aa53adc23",
    "cardNumber": "5342711082294461",
    "cvv": "112",
    "name": "Mahmoud Ragab",
    "expireDate": "01/26",
    "type": "mastercard",
    "userId": 1071,
    "balance": 20,
    "status": "active",
    "createdAt": "2025-01-06T17:42:33.297",
    "updatedAt": "2025-02-22T19:16:28.561"
  },
  {
    "id": 152,
    "bankId": "9eecd3aa-c94f-11ef-80a9-1b749f9c5766",
    "cardNumber": "5342711021598196",
    "cvv": "862",
    "name": "mohammed Nour",
    "expireDate": "01/26",
    "type": "mastercard",
    "userId": 321,
    "balance": 27,
    "status": "active",
    "createdAt": "2025-01-02T21:22:32.477",
    "updatedAt": "2025-02-17T15:58:10.81"
  },
  {
    "id": 154,
    "bankId": "8fe23514-cc18-11ef-a9f4-ab782410d3bb",
    "cardNumber": "5342711000116887",
    "cvv": "515",
    "name": "ZIADAHMED",
    "expireDate": "01/26",
    "type": "mastercard",
    "userId": 720,
    "balance": 5,
    "status": "active",
    "createdAt": "2025-01-06T10:25:56.012",
    "updatedAt": "2025-01-06T10:25:56.012"
  },
  {
    "id": 162,
    "bankId": "0e56f8be-d045-11ef-8a9a-73372a19cd4d",
    "cardNumber": "5342711044273231",
    "cvv": "000",
    "name": "Ahmed adel",
    "expireDate": "01/26",
    "type": "mastercard",
    "userId": 729,
    "balance": 40,
    "status": "active",
    "createdAt": "2025-01-11T17:54:46.601",
    "updatedAt": "2025-02-17T06:42:10.209"
  },
  {
    "id": 143,
    "bankId": "030ecade-c7be-11ef-a94d-f3dd3b31c917",
    "cardNumber": "5342711089556656",
    "cvv": "898",
    "name": "Mohamed Hassan",
    "expireDate": "12/25",
    "type": "mastercard",
    "userId": 1022,
    "balance": 10,
    "status": "active",
    "createdAt": "2024-12-31T21:28:08.798",
    "updatedAt": "2025-01-11T15:57:04.892"
  },
  {
    "id": 135,
    "bankId": "b4e47268-c4b7-11ef-a8e4-5f8a27a78468",
    "cardNumber": "5342711035417276",
    "cvv": "536",
    "name": "Amr Ehab Bedier",
    "expireDate": "12/25",
    "type": "mastercard",
    "userId": 896,
    "balance": 10,
    "status": "active",
    "createdAt": "2024-12-28T01:04:57.49",
    "updatedAt": "2025-02-25T23:17:05.451"
  },
  {
    "id": 157,
    "bankId": "5f17bff4-cc80-11ef-874e-93bcd1e5d232",
    "cardNumber": "5342711088839111",
    "cvv": "818",
    "name": "Mostafa Badr",
    "expireDate": "01/26",
    "type": "mastercard",
    "userId": 1072,
    "balance": 70,
    "status": "active",
    "createdAt": "2025-01-06T22:49:01.956",
    "updatedAt": "2025-02-01T21:53:48.208"
  },
  {
    "id": 127,
    "bankId": "97a5c172-c357-11ef-8eca-4370358dcf0a",
    "cardNumber": "5342711099456483",
    "cvv": "504",
    "name": "Hassan mohamed",
    "expireDate": "12/25",
    "type": "mastercard",
    "userId": 875,
    "balance": 15,
    "status": "active",
    "createdAt": "2024-12-26T07:04:22.001",
    "updatedAt": "2025-02-28T04:13:47.684"
  },
  {
    "id": 165,
    "bankId": "94e42f56-d517-11ef-87c1-2fe6de8898ca",
    "cardNumber": "5342711053214258",
    "cvv": "004",
    "name": "Ahmed Elwany",
    "expireDate": "01/26",
    "type": "mastercard",
    "userId": 1092,
    "balance": 10,
    "status": "active",
    "createdAt": "2025-01-17T21:11:58.322",
    "updatedAt": "2025-01-17T21:11:58.322"
  },
  {
    "id": 159,
    "bankId": "887e1518-cdd0-11ef-9c0b-477238ecd2ae",
    "cardNumber": "5342711031900911",
    "cvv": "060",
    "name": "Youssef raafat",
    "expireDate": "01/26",
    "type": "mastercard",
    "userId": 1076,
    "balance": 20,
    "status": "active",
    "createdAt": "2025-01-08T14:55:20.825",
    "updatedAt": "2025-01-08T14:55:20.825"
  },
  {
    "id": 160,
    "bankId": "a1eb5b32-cdd0-11ef-bec8-2b83b97e5094",
    "cardNumber": "5342711038108393",
    "cvv": "602",
    "name": "ahmedsamy",
    "expireDate": "01/26",
    "type": "mastercard",
    "userId": 1075,
    "balance": 10,
    "status": "active",
    "createdAt": "2025-01-08T14:55:59.401",
    "updatedAt": "2025-01-08T14:55:59.401"
  },
  {
    "id": 166,
    "bankId": "10432a78-d6b0-11ef-9875-9700e3cae8f4",
    "cardNumber": "5342711096606825",
    "cvv": "611",
    "name": "Abdulhameed Lkady",
    "expireDate": "01/26",
    "type": "mastercard",
    "userId": 1095,
    "balance": 100,
    "status": "active",
    "createdAt": "2025-01-19T21:55:35.617",
    "updatedAt": "2025-01-19T21:55:35.617"
  },
  {
    "id": 158,
    "bankId": "33e09d54-cd45-11ef-8e93-bb4c1a1e79c2",
    "cardNumber": "5342711024563031",
    "cvv": "443",
    "name": "Yehia Heiba",
    "expireDate": "01/26",
    "type": "mastercard",
    "userId": 857,
    "balance": 35,
    "status": "active",
    "createdAt": "2025-01-07T22:17:58.273",
    "updatedAt": "2025-01-27T23:55:47.644"
  },
  {
    "id": 163,
    "bankId": "c5c8c770-6b4b-11ef-b3fd-137eb72e468d",
    "cardNumber": "5342711073052423",
    "cvv": "508",
    "name": "Ahmed Maher",
    "expireDate": "09/30",
    "type": "mastercard",
    "userId": 650,
    "balance": 10,
    "status": "active",
    "createdAt": "2025-01-11T18:12:40.013",
    "updatedAt": "2025-01-11T18:12:40.013"
  },
  {
    "id": 131,
    "bankId": "0a682bd6-c485-11ef-b6fc-33407f9650b4",
    "cardNumber": "5342711006075186",
    "cvv": "704",
    "name": "MOSTAFA SALAH",
    "expireDate": "12/25",
    "type": "mastercard",
    "userId": 873,
    "balance": 15,
    "status": "active",
    "createdAt": "2024-12-27T19:02:16.349",
    "updatedAt": "2025-01-12T16:46:51.662"
  },
  {
    "id": 164,
    "bankId": "53aa2c30-d28c-11ef-b51e-abbe8a8ce649",
    "cardNumber": "5342711009939024",
    "cvv": "424",
    "name": "Mohamed Elshafey Aly",
    "expireDate": "01/26",
    "type": "mastercard",
    "userId": 1090,
    "balance": 5,
    "status": "active",
    "createdAt": "2025-01-14T15:30:18.681",
    "updatedAt": "2025-01-14T15:30:18.681"
  },
  {
    "id": 161,
    "bankId": "982e5624-ced1-11ef-a228-fba8572b90ed",
    "cardNumber": "5342711064188533",
    "cvv": "726",
    "name": "Osama Adly Eldahlan",
    "expireDate": "01/26",
    "type": "mastercard",
    "userId": 1069,
    "balance": 81,
    "status": "active",
    "createdAt": "2025-01-09T21:35:26.159",
    "updatedAt": "2025-01-13T04:29:07.377"
  },
  {
    "id": 122,
    "bankId": "6a3dcec6-c232-11ef-a3e3-a37f2316d81f",
    "cardNumber": "5342711048924565",
    "cvv": "535",
    "name": "Ziaderaqy",
    "expireDate": "12/25",
    "type": "mastercard",
    "userId": 855,
    "balance": 27,
    "status": "active",
    "createdAt": "2024-12-24T20:05:44.135",
    "updatedAt": "2025-02-25T17:42:31.51"
  },
  {
    "id": 142,
    "bankId": "6d85f4da-c75c-11ef-9e84-2b535fd48ddb",
    "cardNumber": "5342711004276067",
    "cvv": "558",
    "name": "walid mohamed hassan",
    "expireDate": "12/25",
    "type": "mastercard",
    "userId": 999,
    "balance": 20,
    "status": "active",
    "createdAt": "2024-12-31T09:49:19.323",
    "updatedAt": "2025-01-13T21:37:00.575"
  },
  {
    "id": 137,
    "bankId": "847d256a-c5e9-11ef-9729-afe058743963",
    "cardNumber": "5342711034658565",
    "cvv": "527",
    "name": "Youssef AlJameel",
    "expireDate": "12/25",
    "type": "mastercard",
    "userId": 976,
    "balance": 10,
    "status": "active",
    "createdAt": "2024-12-29T13:34:04.841",
    "updatedAt": "2025-01-18T17:21:44.707"
  },
  {
    "id": 169,
    "bankId": "93b35780-dd94-11ef-8dff-13d91226eacc",
    "cardNumber": "5342711009306059",
    "cvv": "786",
    "name": "Nour Eldeen",
    "expireDate": "01/26",
    "type": "mastercard",
    "userId": 1103,
    "balance": 20,
    "status": "active",
    "createdAt": "2025-01-28T16:26:28.825",
    "updatedAt": "2025-02-25T17:24:00.98"
  },
  {
    "id": 141,
    "bankId": "0d412392-c757-11ef-8ceb-db09e7851b22",
    "cardNumber": "5342711087963847",
    "cvv": "088",
    "name": "Hamzah mustafa",
    "expireDate": "12/25",
    "type": "mastercard",
    "userId": 1002,
    "balance": 22,
    "status": "active",
    "createdAt": "2024-12-31T09:11:09.221",
    "updatedAt": "2025-01-24T20:02:46.632"
  },
  {
    "id": 168,
    "bankId": "171b41e4-db6c-11ef-8289-7706dc34d133",
    "cardNumber": "5342711073979955",
    "cvv": "900",
    "name": "Zezo Abas",
    "expireDate": "01/26",
    "type": "mastercard",
    "userId": 988,
    "balance": 5,
    "status": "active",
    "createdAt": "2025-01-25T22:31:35.226",
    "updatedAt": "2025-01-25T22:31:35.226"
  },
  {
    "id": 145,
    "bankId": "13a5510e-c838-11ef-95a8-1b43920e9076",
    "cardNumber": "5342711029093364",
    "cvv": "362",
    "name": "Mahmoud Mobarez",
    "expireDate": "01/26",
    "type": "mastercard",
    "userId": 1036,
    "balance": 22,
    "status": "active",
    "createdAt": "2025-01-01T12:01:28.188",
    "updatedAt": "2025-01-27T01:02:56.184"
  },
  {
    "id": 126,
    "bankId": "099d6786-c2e9-11ef-b5d8-cfc19ed43051",
    "cardNumber": "5342711067575298",
    "cvv": "936",
    "name": "Kinan Mohsen",
    "expireDate": "12/25",
    "type": "mastercard",
    "userId": 748,
    "balance": 52,
    "status": "active",
    "createdAt": "2024-12-25T17:53:12.593",
    "updatedAt": "2025-02-08T14:41:42.085"
  },
  {
    "id": 170,
    "bankId": "afed525c-df29-11ef-b17f-6b64d8bc82b8",
    "cardNumber": "5342711003576335",
    "cvv": "631",
    "name": "omar a",
    "expireDate": "01/26",
    "type": "mastercard",
    "userId": 1066,
    "balance": 5,
    "status": "active",
    "createdAt": "2025-01-30T16:46:23.313",
    "updatedAt": "2025-01-30T16:46:23.313"
  },
  {
    "id": 146,
    "bankId": "ca9d1aba-c868-11ef-be7e-4fb348daa043",
    "cardNumber": "5342711010318366",
    "cvv": "713",
    "name": "abdelrahman el werdany",
    "expireDate": "01/26",
    "type": "mastercard",
    "userId": 1048,
    "balance": 158,
    "status": "active",
    "createdAt": "2025-01-01T17:50:13.103",
    "updatedAt": "2025-02-02T21:44:44.06"
  },
  {
    "id": 129,
    "bankId": "22201858-c3b1-11ef-b1ef-b3b0c9f0a8c4",
    "cardNumber": "5342711097249054",
    "cvv": "119",
    "name": "Osama Salah",
    "expireDate": "12/25",
    "type": "mastercard",
    "userId": 351,
    "balance": 29,
    "status": "active",
    "createdAt": "2024-12-26T17:45:21.422",
    "updatedAt": "2025-02-04T14:52:10.322"
  },
  {
    "id": 150,
    "bankId": "41a8bb58-c924-11ef-ae88-4b6d141daa4f",
    "cardNumber": "5342711092090529",
    "cvv": "082",
    "name": "Mahmoud",
    "expireDate": "01/26",
    "type": "mastercard",
    "userId": 984,
    "balance": 180,
    "status": "active",
    "createdAt": "2025-01-02T16:12:06.099",
    "updatedAt": "2025-02-13T07:03:19.584"
  },
  {
    "id": 153,
    "bankId": "b7ef3f5e-ca4f-11ef-9c31-0352b8d9bf98",
    "cardNumber": "5342711005981434",
    "cvv": "070",
    "name": "MAHER TARIK",
    "expireDate": "01/26",
    "type": "mastercard",
    "userId": 1065,
    "balance": 490,
    "status": "active",
    "createdAt": "2025-01-04T03:55:41.457",
    "updatedAt": "2025-02-12T21:18:20.716"
  },
  {
    "id": 155,
    "bankId": "730a7c66-cc55-11ef-bc91-8fd82bbdd76d",
    "cardNumber": "5342711055698987",
    "cvv": "541",
    "name": "AHMED RAAFAT",
    "expireDate": "01/26",
    "type": "mastercard",
    "userId": 1068,
    "balance": 6432,
    "status": "active",
    "createdAt": "2025-01-06T17:41:42.795",
    "updatedAt": "2025-02-23T21:32:57.207"
  },
  {
    "id": 133,
    "bankId": "5dcf5006-c485-11ef-8584-3374d1b834a6",
    "cardNumber": "5342711079849160",
    "cvv": "111",
    "name": "Mohab Gabber",
    "expireDate": "12/25",
    "type": "mastercard",
    "userId": 676,
    "balance": 115,
    "status": "active",
    "createdAt": "2024-12-27T19:04:42.341",
    "updatedAt": "2025-02-27T10:07:44.987"
  },
  {
    "id": 171,
    "bankId": "5a1b7a28-df49-11ef-81a4-179a2e134a59",
    "cardNumber": "5342711029374103",
    "cvv": "102",
    "name": "RehabAttya",
    "expireDate": "01/26",
    "type": "mastercard",
    "userId": 1105,
    "balance": 9,
    "status": "active",
    "createdAt": "2025-01-30T20:33:06.433",
    "updatedAt": "2025-01-30T20:33:06.433"
  },
  {
    "id": 172,
    "bankId": "b7125c36-e1ad-11ef-a256-af7a7998c112",
    "cardNumber": "5342711035213832",
    "cvv": "701",
    "name": "Helmy Allam",
    "expireDate": "02/26",
    "type": "mastercard",
    "userId": 1107,
    "balance": 21,
    "status": "active",
    "createdAt": "2025-02-02T21:36:27.681",
    "updatedAt": "2025-02-02T21:36:27.681"
  },
  {
    "id": 173,
    "bankId": "d6192a24-e1ad-11ef-989b-f799ef495aa9",
    "cardNumber": "5342711017402841",
    "cvv": "042",
    "name": "Fatma Ehab",
    "expireDate": "02/26",
    "type": "mastercard",
    "userId": 1108,
    "balance": 7,
    "status": "active",
    "createdAt": "2025-02-02T21:37:24.059",
    "updatedAt": "2025-02-02T21:37:24.059"
  },
  {
    "id": 174,
    "bankId": "39074806-e1b2-11ef-a648-6b72e8b2b608",
    "cardNumber": "5342711019743556",
    "cvv": "902",
    "name": "Mahmoud",
    "expireDate": "02/26",
    "type": "mastercard",
    "userId": 1109,
    "balance": 6,
    "status": "active",
    "createdAt": "2025-02-02T22:08:42.014",
    "updatedAt": "2025-02-02T22:08:42.014"
  },
  {
    "id": 175,
    "bankId": "a06dd3e6-e209-11ef-bdad-d3ea7de03e2c",
    "cardNumber": "5342711055612251",
    "cvv": "622",
    "name": "malak wahab allah",
    "expireDate": "02/26",
    "type": "mastercard",
    "userId": 1110,
    "balance": 5,
    "status": "active",
    "createdAt": "2025-02-03T08:34:26.358",
    "updatedAt": "2025-02-03T08:34:26.358"
  },
  {
    "id": 177,
    "bankId": "97c455f8-e48e-11ef-bcd2-233c9778731a",
    "cardNumber": "5342711052879978",
    "cvv": "659",
    "name": "Mostsfa mohammed",
    "expireDate": "06/26",
    "type": "mastercard",
    "userId": 1115,
    "balance": 15,
    "status": "active",
    "createdAt": "2025-02-06T13:31:26.164",
    "updatedAt": "2025-02-06T15:35:12.228"
  },
  {
    "id": 178,
    "bankId": "8d729508-e626-11ef-b4d7-239072f6ff3a",
    "cardNumber": "5342711060937479",
    "cvv": "503",
    "name": "Mohamed Ayman",
    "expireDate": "02/26",
    "type": "mastercard",
    "userId": 927,
    "balance": 6,
    "status": "active",
    "createdAt": "2025-02-08T14:11:38.648",
    "updatedAt": "2025-02-08T14:11:38.648"
  },
  {
    "id": 176,
    "bankId": "f101b1dc-e44e-11ef-9cb2-bfc4a765325d",
    "cardNumber": "5342711000961845",
    "cvv": "609",
    "name": "MOHAMMED OSMAN",
    "expireDate": "06/26",
    "type": "mastercard",
    "userId": 1113,
    "balance": 16,
    "status": "active",
    "createdAt": "2025-02-06T05:55:50.109",
    "updatedAt": "2025-02-10T18:14:44.726"
  },
  {
    "id": 180,
    "bankId": "45e932cc-eae1-11ef-bbfb-9b444a56007e",
    "cardNumber": "5342711007393232",
    "cvv": "286",
    "name": "Amr",
    "expireDate": "02/26",
    "type": "mastercard",
    "userId": 1124,
    "balance": 65,
    "status": "active",
    "createdAt": "2025-02-14T14:38:13.064",
    "updatedAt": "2025-02-14T19:25:05.936"
  },
  {
    "id": 181,
    "bankId": "47108b66-ec2e-11ef-b999-d36e516d9a3d",
    "cardNumber": "5342711026579753",
    "cvv": "161",
    "name": "Abdelrahman Moussa",
    "expireDate": "02/26",
    "type": "mastercard",
    "userId": 809,
    "balance": 5,
    "status": "active",
    "createdAt": "2025-02-16T06:22:18.751",
    "updatedAt": "2025-02-16T06:22:18.751"
  },
  {
    "id": 182,
    "bankId": "e903884e-ee66-11ef-af02-b3ab38f2f8fc",
    "cardNumber": "5342711064974205",
    "cvv": "907",
    "name": "Adham alaa",
    "expireDate": "02/26",
    "type": "mastercard",
    "userId": 1128,
    "balance": 10,
    "status": "active",
    "createdAt": "2025-02-19T02:12:27.919",
    "updatedAt": "2025-02-19T02:12:27.919"
  },
  {
    "id": 183,
    "bankId": "e9813d34-eef2-11ef-9ee3-9b5eb3f457cc",
    "cardNumber": "5342711004669832",
    "cvv": "606",
    "name": "mahmoud abdelazeez",
    "expireDate": "02/26",
    "type": "mastercard",
    "userId": 1127,
    "balance": 5,
    "status": "active",
    "createdAt": "2025-02-19T18:55:22.91",
    "updatedAt": "2025-02-19T18:55:22.91"
  },
  {
    "id": 179,
    "bankId": "f19c63c8-e7ee-11ef-9795-bbf4bae3b31c",
    "cardNumber": "5342711098947409",
    "cvv": "691",
    "name": "Abdelrhman Galal",
    "expireDate": "02/26",
    "type": "mastercard",
    "userId": 1120,
    "balance": 215,
    "status": "active",
    "createdAt": "2025-02-10T20:38:35.933",
    "updatedAt": "2025-02-22T20:22:52.588"
  },
  {
    "id": 184,
    "bankId": "deff53ee-f18d-11ef-91bd-1b5d13d14040",
    "cardNumber": "5342711088608664",
    "cvv": "719",
    "name": "Mena",
    "expireDate": "02/26",
    "type": "mastercard",
    "userId": 1132,
    "balance": 5,
    "status": "active",
    "createdAt": "2025-02-23T02:28:53.019",
    "updatedAt": "2025-02-23T02:28:53.019"
  },
  {
    "id": 185,
    "bankId": "de62b7b0-f1eb-11ef-8383-ab752f084c8b",
    "cardNumber": "5342711011848171",
    "cvv": "797",
    "name": "Abdelrahman Yasser",
    "expireDate": "02/26",
    "type": "mastercard",
    "userId": 1133,
    "balance": 60,
    "status": "active",
    "createdAt": "2025-02-23T13:42:07.661",
    "updatedAt": "2025-02-23T13:42:07.661"
  },
  {
    "id": 148,
    "bankId": "cc0c98c4-c87e-11ef-aa9d-0347c4ecfab7",
    "cardNumber": "5342711009985811",
    "cvv": "257",
    "name": "Ahmed saad",
    "expireDate": "01/26",
    "type": "mastercard",
    "userId": 637,
    "balance": 431,
    "status": "active",
    "createdAt": "2025-01-01T20:28:42.46",
    "updatedAt": "2025-02-23T13:57:47.234"
  },
  {
    "id": 186,
    "bankId": "8452bdf8-f3c4-11ef-9801-0b14acfc8275",
    "cardNumber": "5342711002056560",
    "cvv": "307",
    "name": "Mohamed Osman",
    "expireDate": "02/26",
    "type": "mastercard",
    "userId": 1134,
    "balance": 5,
    "status": "active",
    "createdAt": "2025-02-25T22:05:43.233",
    "updatedAt": "2025-02-25T22:05:43.233"
  }
]
